transitions/__init__.py
transitions/__init__.pyi
transitions/core.py
transitions/core.pyi
transitions/experimental/__init__.py
transitions/experimental/utils.py
transitions/experimental/utils.pyi
transitions/extensions/__init__.py
transitions/extensions/__init__.pyi
transitions/extensions/asyncio.py
transitions/extensions/asyncio.pyi
transitions/extensions/diagrams.py
transitions/extensions/diagrams.pyi
transitions/extensions/diagrams_base.py
transitions/extensions/diagrams_base.pyi
transitions/extensions/diagrams_graphviz.py
transitions/extensions/diagrams_graphviz.pyi
transitions/extensions/diagrams_mermaid.py
transitions/extensions/diagrams_mermaid.pyi
transitions/extensions/diagrams_pygraphviz.py
transitions/extensions/diagrams_pygraphviz.pyi
transitions/extensions/factory.py
transitions/extensions/factory.pyi
transitions/extensions/locking.py
transitions/extensions/locking.pyi
transitions/extensions/markup.py
transitions/extensions/markup.pyi
transitions/extensions/nesting.py
transitions/extensions/nesting.pyi
transitions/extensions/states.py
transitions/extensions/states.pyi
transitions/py.typed
transitions/version.py
transitions/version.pyi
pytransitions-0.9.2rc1.dist-info/LICENSE
pytransitions-0.9.2rc1.dist-info/METADATA
pytransitions-0.9.2rc1.dist-info/WHEEL
pytransitions-0.9.2rc1.dist-info/RECORD
