Metadata-Version: 2.1
Name: pytransitions
Version: 0.9.2rc1
Summary: A lightweight, object-oriented Python state machine implementation with many extensions.
License: MIT
Author: haonv
Author-email: vanhao1915@gmail.com
Requires-Python: >=3.10,<4.0
Classifier: License :: OSI Approved :: MIT License
Classifier: Programming Language :: Python :: 3
Classifier: Programming Language :: Python :: 3.10
Classifier: Programming Language :: Python :: 3.11
Classifier: Programming Language :: Python :: 3.12
Classifier: Programming Language :: Python :: 2
Classifier: Programming Language :: Python :: 2.7
Classifier: Programming Language :: Python :: 3.8
Classifier: Programming Language :: Python :: 3.9
Requires-Dist: six (>=1.10)
